richstyle/__init__.py
richstyle/colors/character_color_map.py
richstyle/colors/color.py
richstyle/colors/gradient.py
richstyle/colors/parser/from_hsl.py
richstyle/colors/parser/from_html.py
richstyle/colors/parser/rainbow_text.py
richstyle/colors/parser/random_color.py
richstyle/colors/presets.py
richstyle/core/combine_text.py
richstyle/core/style.py
richstyle/enums/gradient_type.py
richstyle/enums/layers.py
richstyle/styles/background.py
richstyle/styles/bold.py
richstyle/styles/bullet_list.py
richstyle/styles/foreground.py
richstyle/styles/italic.py
richstyle/styles/strikethrough.py
richstyle/styles/underline.py
richstyle/utils/prints/debug.py
richstyle/utils/prints/error.py
richstyle/utils/prints/info.py
richstyle/utils/prints/mutable.py
richstyle/utils/prints/success.py
richstyle/utils/prints/timed.py
richstyle/utils/prints/warn.py
richstyle/utils/supports_ansi.py
richstyle-1.0.dist-info/LICENSE
richstyle-1.0.dist-info/METADATA
richstyle-1.0.dist-info/WHEEL
richstyle-1.0.dist-info/RECORD
