Metadata-Version: 2.3
Name: richstyle
Version: 1.0
Summary: A Python library for creating and applying full-color, linear, and circular gradients to text with easy color management. Includes utilities for ANSI styling, colored prints, and more.
License: MIT
Keywords: python,color,colors,easy,cmd,app,manage,text,colour,ansi,terminal,gradient,gradients,bold,italic,underscore,command,commands
Author: PcoiDev
Requires-Python: >=3.6
Classifier: Intended Audience :: Developers
Classifier: License :: OSI Approved :: MIT License
Classifier: Operating System :: MacOS :: MacOS X
Classifier: Operating System :: Microsoft :: Windows
Classifier: Operating System :: Unix
Classifier: Programming Language :: Python :: 3
Classifier: Programming Language :: Python :: 3.6
Classifier: Programming Language :: Python :: 3.7
Classifier: Programming Language :: Python :: 3.8
Classifier: Programming Language :: Python :: 3.9
Classifier: Programming Language :: Python :: 3.10
Classifier: Programming Language :: Python :: 3.11
Classifier: Programming Language :: Python :: 3.12
Classifier: Programming Language :: Python :: 3.13
Requires-Dist: dataclasses (>=0.6)
Requires-Dist: typing (>=3.7.4.3)
